LICENSE
MANIFEST.in
README.rst
README.txt
setup.py
upload.bat
radware_os_lb_v2_newton/__init__.py
radware_os_lb_v2_newton/base_v2_driver.py
radware_os_lb_v2_newton/exceptions.py
radware_os_lb_v2_newton/my_driver.py
radware_os_lb_v2_newton/rest_client.py
radware_os_lb_v2_newton/v2_driver.py
radware_os_lb_v2_newton.egg-info/PKG-INFO
radware_os_lb_v2_newton.egg-info/SOURCES.txt
radware_os_lb_v2_newton.egg-info/dependency_links.txt
radware_os_lb_v2_newton.egg-info/not-zip-safe
radware_os_lb_v2_newton.egg-info/top_level.txt